yunetas-0.5.8.dist-info/METADATA
yunetas-0.5.8.dist-info/WHEEL
yunetas-0.5.8.dist-info/entry_points.txt
yunetas/__init__.py
yunetas/__main__.py
yunetas/__version__.py
yunetas/main.py
yunetas/my_venv.py
yunetas-0.5.8.dist-info/RECORD
