Metadata-Version: 2.1
Name: yunetas
Version: 0.5.8
Summary: TUI (Terminal User Interface) of Yunetas
Author-Email: rmm <rosa.martinez@artgins.com>
License: MIT
Requires-Python: >=3.7
Requires-Dist: typer[all]>=0.9.0
